MANIFEST.in
README
__init__.py
__pkginfo__.py
entities.py
hooks.py
logformat.py
schema.py
setup.py
site_cubicweb.py
testutils.py
bin/narval
cubicweb_narval.egg-info/PKG-INFO
cubicweb_narval.egg-info/SOURCES.txt
cubicweb_narval.egg-info/dependency_links.txt
cubicweb_narval.egg-info/requires.txt
cubicweb_narval.egg-info/top_level.txt
data/cubes.narval.css
data/cubes.narval.js
examples/narval-cw-sources.ini
examples/narval.ini
i18n/en.po
i18n/fr.po
migration/3.0.0_Any.py
migration/3.2.1_Any.py
migration/4.0.0_Any.py
migration/4.2.1_Any.py
migration/postcreate.py
migration/precreate.py
narvalbot/__init__.py
narvalbot/__pkginfo__.py
narvalbot/engine.py
narvalbot/main.py
narvalbot/server.py
narvalbot/share/README
schema/_regproc.postgres.sql
test/test_functional.py
test/test_narval.py
test/unittest_security.py
test/unittest_views.py
views/__init__.py
views/bot.py
views/plan.py
views/recipe.py
views/startplan.py
views/startup.py
wdoc/narval_architecture_en.rst
wdoc/narval_quick_start_en.rst
wdoc/toc.xml