Metadata-Version: 1.0
Name: cubicweb-narval
Version: 4.2.3
Summary: the Narval agent
Home-page: http://www.cubicweb.org/project/cubicweb-narval
Author: LOGILAB S.A. (Paris, FRANCE)
Author-email: contact@logilab.fr
License: LGPL
Platform: UNKNOWN
